LICENSE.md
README.md
pandoctylus/__init__.py
pandoctylus/pandoctylus.py
pandoctylus-0.2.0.dist-info/METADATA
pandoctylus-0.2.0.dist-info/WHEEL
pandoctylus-0.2.0.dist-info/licenses/LICENSE.md
pandoctylus-0.2.0.dist-info/RECORD
