Metadata-Version: 2.4
Name: pandoctylus
Version: 0.2.0
Summary: A crazy and opinionated way of generating documents.
Author-email: Sebastian Schaetz <seb.schaetz@gmail.com>
License-Expression: MIT
License-File: LICENSE.md
Requires-Python: >=3.9
Requires-Dist: docxtpl
Requires-Dist: pypandoc-binary
Requires-Dist: pyyaml
Provides-Extra: dev
Requires-Dist: black; extra == 'dev'
Requires-Dist: isort; extra == 'dev'
Requires-Dist: mypy; extra == 'dev'
Requires-Dist: pytest; extra == 'dev'
Requires-Dist: pytest-cov; extra == 'dev'
